sysid_pem_toolbox/__init__.py
sysid_pem_toolbox/sysid_pem.py
tests/__init__.py
tests/test_sysid.py
sysid_pem_toolbox-0.1.0.dist-info/LICENSE
sysid_pem_toolbox-0.1.0.dist-info/METADATA
sysid_pem_toolbox-0.1.0.dist-info/WHEEL
sysid_pem_toolbox-0.1.0.dist-info/top_level.txt
sysid_pem_toolbox-0.1.0.dist-info/RECORD
